{
  "name": "United Earth Government Police Force",
  "type": "soldierType",
  "img": "icons/svg/item-bag.svg",
  "data": {
    "catchPhrase": "When the going gets tough, we’ll get tougher",
    "characteristics": {
      "str": {
        "value": 25,
        "advancement": 0
      },
      "t": {
        "value": 25,
        "advancement": 0
      },
      "ag": {
        "value": 25,
        "advancement": 0
      },
      "wfr": {
        "value": 25,
        "advancement": 1
      },
      "wfm": {
        "value": 25,
        "advancement": 0
      },
      "int": {
        "value": 25,
        "advancement": 0
      },
      "per": {
        "value": 25,
        "advancement": 0
      },
      "cr": {
        "value": 25,
        "advancement": 0
      },
      "ch": {
        "value": 25,
        "advancement": 0
      },
      "ld": {
        "value": 25,
        "advancement": 1
      }
    },
    "mythicCharacteristics": {
      "str": 0,
      "t": 0,
      "ag": 0
    },
    "tier": 2,
    "expCost": 1000,
    "upbringings": [],
    "trainings": ["basic", "infantry"],
    "height": {
      "min": 170,
      "max": 193
    },
    "weight": {
      "min": 58,
      "max": 104
    },
    "size": "normal",
    "specialRules": [
      "The Policeman begins with the Human Weaponry Racial Training at Character Creation.",
      "The Policeman begins with one Skill of their choosing at +10 at Character Creation.",
      "The Policeman begins with the Human Law Education at Character Creation.",
      "Police cannot Purchase anything from the Covenant and Forerunner Armories. Anything purchased from the UNSC Armory is at double the Price, unless the weapon specifies otherwise.",
      "<b>PROTECT AND SERVE</b>: When around Civilians in distress or in danger, Policemen gain a +20 Bonus in Courage.",
      "<b>CRISIS</b>: In times of Crisis, the Policeman gains access to the time period’s UNSC Standard BDU Armor. During this, the Character also has the option to replace their two Flashbang Grenades with two M9 Dual-Purpose Grenades. The is not permanent, and only lasts during major events, such as Covenant invasions, Insurrectionist Attacks, and other GM-specified events.",
      "<b>SQUAD UP</b>: When with others from the United Earth Government Police Force; these Characters gain a +5 Bonus to Courage. The Characters also gain a +10 Bonus to Warfare Melee and Warfare Range Tests when taking Combined Actions."
    ],
    "equipmentPacks": [{
      "name": "Point Man Equipment",
      "equipment": [{
        "0": "dG2ZJhbbjJkR6pxc"
      }, {
        "0": "dG6ZJhbbjJkRapxc",
        "1": "dG6ZJhbbjJkRcpxc"
      }]
    }, {
      "name": "Close-Range Equipment"
    }, {
      "name": "CQC Equipment"
    }, {
      "name": "Marksman Equipment"
    }]
  },
  "effects": [],
  "sort": 0,
  "flags": {},
  "permission": {
    "default": 0
  },
  "_id": "dG1ZJhbbjJkR1pxc"
}
